{
    "total": [
        {
            "id": "100007812407701",
            "count": 0
        },
        {
            "id": "100012630407733",
            "count": 0
        },
        {
            "id": "100012836863377",
            "count": 3
        },
        {
            "id": "100022213373397",
            "count": 0
        },
        {
            "id": "100024402034958",
            "count": 0
        },
        {
            "id": "100024490128272",
            "count": 0
        },
        {
            "id": "100025035174355",
            "count": 0
        },
        {
            "id": "100026707747289",
            "count": 0
        },
        {
            "id": "100027460655399",
            "count": 0
        },
        {
            "id": "100029969779549",
            "count": 0
        },
        {
            "id": "100037177470830",
            "count": 0
        },
        {
            "id": "100037228920409",
            "count": 0
        },
        {
            "id": "100038178249832",
            "count": 0
        },
        {
            "id": "100038400139310",
            "count": 0
        },
        {
            "id": "100041256037506",
            "count": 0
        },
        {
            "id": "100041503544242",
            "count": 0
        },
        {
            "id": "100042815376514",
            "count": 0
        },
        {
            "id": "100043722909992",
            "count": 0
        },
        {
            "id": "100044280846102",
            "count": 0
        },
        {
            "id": "100045199034947",
            "count": 0
        },
        {
            "id": "100045955402446",
            "count": 0
        },
        {
            "id": "100046078387032",
            "count": 64
        },
        {
            "id": "100047475605358",
            "count": 0
        },
        {
            "id": "100048276390483",
            "count": 0
        },
        {
            "id": "100048839768713",
            "count": 0
        },
        {
            "id": "100049137848673",
            "count": 0
        },
        {
            "id": "100050232380791",
            "count": 0
        },
        {
            "id": "100050972042794",
            "count": 0
        },
        {
            "id": "100051245422745",
            "count": 0
        },
        {
            "id": "100051317467414",
            "count": 0
        },
        {
            "id": "100051901751643",
            "count": 0
        },
        {
            "id": "100052423595627",
            "count": 0
        },
        {
            "id": "100052677201214",
            "count": 0
        },
        {
            "id": "100052914630016",
            "count": 0
        },
        {
            "id": "100053459353143",
            "count": 0
        },
        {
            "id": "100053629447130",
            "count": 0
        },
        {
            "id": "100054661677253",
            "count": 0
        },
        {
            "id": "100055314635973",
            "count": 5
        },
        {
            "id": "100055555893056",
            "count": 0
        },
        {
            "id": "100055593937770",
            "count": 0
        },
        {
            "id": "100055697006843",
            "count": 0
        },
        {
            "id": "100056866672949",
            "count": 0
        },
        {
            "id": "100057134903486",
            "count": 0
        },
        {
            "id": "100058175524214",
            "count": 0
        },
        {
            "id": "100058645046993",
            "count": 0
        },
        {
            "id": "100058842408735",
            "count": 0
        },
        {
            "id": "100059682517481",
            "count": 12
        },
        {
            "id": "100059884234133",
            "count": 0
        },
        {
            "id": "100060430131474",
            "count": 0
        },
        {
            "id": "100060936063100",
            "count": 0
        },
        {
            "id": "100061422077496",
            "count": 0
        },
        {
            "id": "100062573980288",
            "count": 0
        },
        {
            "id": "100063469263222",
            "count": 0
        },
        {
            "id": "100063576116914",
            "count": 0
        },
        {
            "id": "100064065200879",
            "count": 0
        },
        {
            "id": "100064730705784",
            "count": 7
        },
        {
            "id": "100064864904115",
            "count": 0
        },
        {
            "id": "100065333342419",
            "count": 0
        },
        {
            "id": "100066576243307",
            "count": 0
        },
        {
            "id": "100068201213552",
            "count": 0
        },
        {
            "id": "100068545177109",
            "count": 0
        },
        {
            "id": "100068676198239",
            "count": 170
        },
        {
            "id": "100068867336823",
            "count": 0
        },
        {
            "id": "100068946031730",
            "count": 0
        },
        {
            "id": "100069756806880",
            "count": 0
        },
        {
            "id": "100069855820548",
            "count": 0
        },
        {
            "id": "100070297303497",
            "count": 24
        },
        {
            "id": "100070663291260",
            "count": 114
        },
        {
            "id": "100070994245446",
            "count": 0
        },
        {
            "id": "100071049767402",
            "count": 0
        },
        {
            "id": "100072255319444",
            "count": 0
        },
        {
            "id": "100072257869682",
            "count": 3
        },
        {
            "id": "100072805663375",
            "count": 0
        },
        {
            "id": "100073237120661",
            "count": 0
        },
        {
            "id": "100073610085414",
            "count": 1
        },
        {
            "id": "100073980825437",
            "count": 0
        },
        {
            "id": "100074037878886",
            "count": 4
        },
        {
            "id": "100074283784305",
            "count": 2
        },
        {
            "id": "100074576227236",
            "count": 51
        },
        {
            "id": "100074630951171",
            "count": 0
        },
        {
            "id": "100074959639257",
            "count": 0
        },
        {
            "id": "100075027864137",
            "count": 0
        },
        {
            "id": "100076380444403",
            "count": 0
        },
        {
            "id": "100076507910016",
            "count": 3
        },
        {
            "id": "100076535876327",
            "count": 0
        },
        {
            "id": "100077080645895",
            "count": 1
        },
        {
            "id": "100077452946588",
            "count": 0
        },
        {
            "id": "100077594163249",
            "count": 0
        },
        {
            "id": "100078012585693",
            "count": 1
        },
        {
            "id": "100078205730156",
            "count": 0
        },
        {
            "id": "100078442474256",
            "count": 21
        },
        {
            "id": "100078681949049",
            "count": 12
        },
        {
            "id": "100079018110551",
            "count": 0
        },
        {
            "id": "100079021664219",
            "count": 0
        },
        {
            "id": "100079071850141",
            "count": 1
        },
        {
            "id": "100079325465179",
            "count": 0
        },
        {
            "id": "100079865631656",
            "count": 0
        },
        {
            "id": "100080143350454",
            "count": 0
        },
        {
            "id": "100080506235887",
            "count": 3
        },
        {
            "id": "100080971575866",
            "count": 0
        },
        {
            "id": "100082301112064",
            "count": 238
        },
        {
            "id": "100082589250845",
            "count": 0
        },
        {
            "id": "100082684489410",
            "count": 0
        },
        {
            "id": "100082709616378",
            "count": 0
        },
        {
            "id": "100083258926393",
            "count": 0
        },
        {
            "id": "100083853953516",
            "count": 50
        },
        {
            "id": "100070914806298",
            "count": 2
        },
        {
            "id": "100073237527456",
            "count": 25
        }
    ],
    "week": [
        {
            "id": "100007812407701",
            "count": 0,
            "name": "Trần Phạm Mạnh Hùng"
        },
        {
            "id": "100012630407733",
            "count": 0,
            "name": "Ngọc Linh"
        },
        {
            "id": "100012836863377",
            "count": 0,
            "name": "Ngọ Quang Tiến"
        },
        {
            "id": "100022213373397",
            "count": 0,
            "name": "Sơn Lê"
        },
        {
            "id": "100024402034958",
            "count": 0,
            "name": "Toàn Không Xinh"
        },
        {
            "id": "100024490128272",
            "count": 0,
            "name": "Lệ Tuyết"
        },
        {
            "id": "100025035174355",
            "count": 0,
            "name": "Hoàng Nam"
        },
        {
            "id": "100026707747289",
            "count": 0,
            "name": "Phạm Thoại"
        },
        {
            "id": "100027460655399",
            "count": 0,
            "name": "Trần Đình Thông"
        },
        {
            "id": "100029969779549",
            "count": 0,
            "name": "Nguyen Hoang Viet Lon"
        },
        {
            "id": "100037177470830",
            "count": 0,
            "name": "Ngọc Tuyền"
        },
        {
            "id": "100037228920409",
            "count": 0,
            "name": "BBI HOÀNG THỊ HUYỀN"
        },
        {
            "id": "100038178249832",
            "count": 0,
            "name": "Bui Thinhh ꪜ"
        },
        {
            "id": "100038400139310",
            "count": 0,
            "name": "Hoài Short"
        },
        {
            "id": "100041256037506",
            "count": 0,
            "name": "Teo Van Sang YT"
        },
        {
            "id": "100041503544242",
            "count": 0,
            "name": "Đặng Thùy Trâm"
        },
        {
            "id": "100042815376514",
            "count": 0,
            "name": "Nguyễn Thị Thanh Nga"
        },
        {
            "id": "100043722909992",
            "count": 0,
            "name": "Vũ Trần Phương Nam"
        },
        {
            "id": "100044280846102",
            "count": 0,
            "name": "Dam Thi Ngocanh"
        },
        {
            "id": "100045199034947",
            "count": 0,
            "name": "Vũ Đức"
        },
        {
            "id": "100045955402446",
            "count": 0,
            "name": "Hbang Xinhgai"
        },
        {
            "id": "100046078387032",
            "count": 0,
            "name": "Ṅgüyễṅ's Vïṅh's"
        },
        {
            "id": "100047475605358",
            "count": 0,
            "name": "Thij Vaan"
        },
        {
            "id": "100048276390483",
            "count": 0,
            "name": "Hồ Gia Chánh"
        },
        {
            "id": "100048839768713",
            "count": 0,
            "name": "Phụng Nè"
        },
        {
            "id": "100049137848673",
            "count": 0,
            "name": "Lyy Dubaii"
        },
        {
            "id": "100050232380791",
            "count": 0,
            "name": "Trần Tuấn"
        },
        {
            "id": "100050972042794",
            "count": 0,
            "name": "Đặng Thành Đạt"
        },
        {
            "id": "100051245422745",
            "count": 0,
            "name": "Nguyễn Cường"
        },
        {
            "id": "100051317467414",
            "count": 0,
            "name": "Ng Ngoc Truc Linh"
        },
        {
            "id": "100051901751643",
            "count": 0,
            "name": "Hải Trần"
        },
        {
            "id": "100052423595627",
            "count": 0,
            "name": "Hoàng Xướng"
        },
        {
            "id": "100052677201214",
            "count": 0,
            "name": "Nhung Trần"
        },
        {
            "id": "100052914630016",
            "count": 0,
            "name": "Huyền Trâm"
        },
        {
            "id": "100053459353143",
            "count": 0,
            "name": "Oanh Hoàng"
        },
        {
            "id": "100053629447130",
            "count": 0,
            "name": "Phương's Black's"
        },
        {
            "id": "100054661677253",
            "count": 0,
            "name": "Lê Đình Linh"
        },
        {
            "id": "100055314635973",
            "count": 0,
            "name": "Trúc Ly"
        },
        {
            "id": "100055555893056",
            "count": 0,
            "name": "Ngọc Thuận"
        },
        {
            "id": "100055593937770",
            "count": 0,
            "name": "Mei Dayy"
        },
        {
            "id": "100055697006843",
            "count": 0,
            "name": "Hằng Trần"
        },
        {
            "id": "100056866672949",
            "count": 0,
            "name": "Thư Này Cho Bạn"
        },
        {
            "id": "100057134903486",
            "count": 0,
            "name": "N. Ngọc"
        },
        {
            "id": "100058175524214",
            "count": 0,
            "name": "Nguyễn Đạt"
        },
        {
            "id": "100058645046993",
            "count": 0,
            "name": "Khánh Linh"
        },
        {
            "id": "100058842408735",
            "count": 0,
            "name": "이안히"
        },
        {
            "id": "100059682517481",
            "count": 0,
            "name": "Công Trần"
        },
        {
            "id": "100059884234133",
            "count": 0,
            "name": "Tra My"
        },
        {
            "id": "100060430131474",
            "count": 0,
            "name": "Tần Dương"
        },
        {
            "id": "100060936063100",
            "count": 0,
            "name": "Nguyễn Ngọc"
        },
        {
            "id": "100061422077496",
            "count": 0,
            "name": "N.Đ Quỳnh Zy"
        },
        {
            "id": "100062573980288",
            "count": 0,
            "name": "Lâm Tuyết Hoà"
        },
        {
            "id": "100063469263222",
            "count": 0,
            "name": "Yến Phương"
        },
        {
            "id": "100063576116914",
            "count": 0,
            "name": "Ngoc Anh Phạm"
        },
        {
            "id": "100064065200879",
            "count": 0,
            "name": "Ai Thi"
        },
        {
            "id": "100064730705784",
            "count": 0,
            "name": "Tấn Hưng"
        },
        {
            "id": "100064864904115",
            "count": 0,
            "name": "Cẩm Diên"
        },
        {
            "id": "100065333342419",
            "count": 0,
            "name": "Hà Văn Nhất"
        },
        {
            "id": "100066576243307",
            "count": 0,
            "name": "Bình Nguyễn"
        },
        {
            "id": "100068201213552",
            "count": 0,
            "name": "Thanh Hiếu"
        },
        {
            "id": "100068545177109",
            "count": 0,
            "name": "Nguyễn Phương Thảo"
        },
        {
            "id": "100068676198239",
            "count": 0,
            "name": "Đứcc Annh"
        },
        {
            "id": "100068867336823",
            "count": 0,
            "name": "Nam Vũ"
        },
        {
            "id": "100068946031730",
            "count": 0,
            "name": "Hà Tuan Anh"
        },
        {
            "id": "100069756806880",
            "count": 0,
            "name": "Quyền Tatto"
        },
        {
            "id": "100069855820548",
            "count": 0,
            "name": "Nguyễn Dương"
        },
        {
            "id": "100070297303497",
            "count": 0,
            "name": "Khzin Dthw"
        },
        {
            "id": "100070663291260",
            "count": 0,
            "name": "Trọng Nguyễn"
        },
        {
            "id": "100070994245446",
            "count": 0,
            "name": "NT Ngọc Trúc"
        },
        {
            "id": "100071049767402",
            "count": 0,
            "name": "Vân Anh Kiku"
        },
        {
            "id": "100072255319444",
            "count": 0,
            "name": "Thảo Phương Nek"
        },
        {
            "id": "100072257869682",
            "count": 0,
            "name": "Thậtralàtaobịđẹptrai Lạicòncutinữacơý"
        },
        {
            "id": "100072805663375",
            "count": 0,
            "name": "Phuongg Anhh"
        },
        {
            "id": "100073237120661",
            "count": 0,
            "name": "Tao　Vừa　Đẹp　Trai　Vừa　 Cute　Nhất　Vũ　Trụ"
        },
        {
            "id": "100073610085414",
            "count": 0,
            "name": "Nhất ꪜ"
        },
        {
            "id": "100073980825437",
            "count": 0,
            "name": "Chà-xanh- Trộn-matcha"
        },
        {
            "id": "100074037878886",
            "count": 0,
            "name": "Hữu Bằng"
        },
        {
            "id": "100074283784305",
            "count": 0,
            "name": "Đức Annh"
        },
        {
            "id": "100074576227236",
            "count": 0,
            "name": "Phương Võ"
        },
        {
            "id": "100074630951171",
            "count": 0,
            "name": "Nguyễn Thành Trung"
        },
        {
            "id": "100074959639257",
            "count": 0,
            "name": "Trà Đào Cam Xả"
        },
        {
            "id": "100075027864137",
            "count": 0,
            "name": "ʚMinh Túɞ"
        },
        {
            "id": "100076380444403",
            "count": 0,
            "name": "Đặng Văn Quyết"
        },
        {
            "id": "100076507910016",
            "count": 0,
            "name": "Nguyễn'z Quốc'z Bảo'z"
        },
        {
            "id": "100076535876327",
            "count": 0,
            "name": "Thanh Kim"
        },
        {
            "id": "100077080645895",
            "count": 0,
            "name": "Nguyễn Văn Tuấn"
        },
        {
            "id": "100077452946588",
            "count": 0,
            "name": "Doanh Phạm"
        },
        {
            "id": "100077594163249",
            "count": 0,
            "name": "Khánhh Băngg"
        },
        {
            "id": "100078012585693",
            "count": 0,
            "name": "Thư Đoàn"
        },
        {
            "id": "100078205730156",
            "count": 0,
            "name": "Kim Chun"
        },
        {
            "id": "100078442474256",
            "count": 0,
            "name": "Công Xanh Xinh Đẹp"
        },
        {
            "id": "100078681949049",
            "count": 0,
            "name": "Tý Mi Kèn Cố"
        },
        {
            "id": "100079018110551",
            "count": 0,
            "name": "Nguyễn Ánh Thương"
        },
        {
            "id": "100079021664219",
            "count": 0,
            "name": "Ng QuynhNhu"
        },
        {
            "id": "100079071850141",
            "count": 0,
            "name": "Xu KA"
        },
        {
            "id": "100079325465179",
            "count": 0,
            "name": "Han Nhung"
        },
        {
            "id": "100079865631656",
            "count": 0,
            "name": "Thảo Đâyy"
        },
        {
            "id": "100080143350454",
            "count": 0,
            "name": "Trần Văn An"
        },
        {
            "id": "100080506235887",
            "count": 0,
            "name": "Tấnk Hưynq"
        },
        {
            "id": "100080971575866",
            "count": 0,
            "name": "Hiệu Mikenco"
        },
        {
            "id": "100082301112064",
            "count": 0,
            "name": "Lê Tứn"
        },
        {
            "id": "100082589250845",
            "count": 0,
            "name": "Vân Ank"
        },
        {
            "id": "100082684489410",
            "count": 0,
            "name": "Tý Mất Nick"
        },
        {
            "id": "100082709616378",
            "count": 0,
            "name": "Sang Lê"
        },
        {
            "id": "100083258926393",
            "count": 0,
            "name": "Hà Thu"
        },
        {
            "id": "100083853953516",
            "count": 0,
            "name": "Trần Khang"
        },
        {
            "id": "100070914806298",
            "count": 0,
            "name": "ʚThu Trangɞ"
        },
        {
            "id": "100073237527456",
            "count": 0,
            "name": "Phùng Mỹ Duyên"
        }
    ],
    "day": [
        {
            "id": "100007812407701",
            "count": 0,
            "name": "Trần Phạm Mạnh Hùng"
        },
        {
            "id": "100012630407733",
            "count": 0,
            "name": "Ngọc Linh"
        },
        {
            "id": "100012836863377",
            "count": 0,
            "name": "Ngọ Quang Tiến"
        },
        {
            "id": "100022213373397",
            "count": 0,
            "name": "Sơn Lê"
        },
        {
            "id": "100024402034958",
            "count": 0,
            "name": "Toàn Không Xinh"
        },
        {
            "id": "100024490128272",
            "count": 0,
            "name": "Lệ Tuyết"
        },
        {
            "id": "100025035174355",
            "count": 0,
            "name": "Hoàng Nam"
        },
        {
            "id": "100026707747289",
            "count": 0,
            "name": "Phạm Thoại"
        },
        {
            "id": "100027460655399",
            "count": 0,
            "name": "Trần Đình Thông"
        },
        {
            "id": "100029969779549",
            "count": 0,
            "name": "Nguyen Hoang Viet Lon"
        },
        {
            "id": "100037177470830",
            "count": 0,
            "name": "Ngọc Tuyền"
        },
        {
            "id": "100037228920409",
            "count": 0,
            "name": "BBI HOÀNG THỊ HUYỀN"
        },
        {
            "id": "100038178249832",
            "count": 0,
            "name": "Bui Thinhh ꪜ"
        },
        {
            "id": "100038400139310",
            "count": 0,
            "name": "Hoài Short"
        },
        {
            "id": "100041256037506",
            "count": 0,
            "name": "Teo Van Sang YT"
        },
        {
            "id": "100041503544242",
            "count": 0,
            "name": "Đặng Thùy Trâm"
        },
        {
            "id": "100042815376514",
            "count": 0,
            "name": "Nguyễn Thị Thanh Nga"
        },
        {
            "id": "100043722909992",
            "count": 0,
            "name": "Vũ Trần Phương Nam"
        },
        {
            "id": "100044280846102",
            "count": 0,
            "name": "Dam Thi Ngocanh"
        },
        {
            "id": "100045199034947",
            "count": 0,
            "name": "Vũ Đức"
        },
        {
            "id": "100045955402446",
            "count": 0,
            "name": "Hbang Xinhgai"
        },
        {
            "id": "100046078387032",
            "count": 0,
            "name": "Ṅgüyễṅ's Vïṅh's"
        },
        {
            "id": "100047475605358",
            "count": 0,
            "name": "Thij Vaan"
        },
        {
            "id": "100048276390483",
            "count": 0,
            "name": "Hồ Gia Chánh"
        },
        {
            "id": "100048839768713",
            "count": 0,
            "name": "Phụng Nè"
        },
        {
            "id": "100049137848673",
            "count": 0,
            "name": "Lyy Dubaii"
        },
        {
            "id": "100050232380791",
            "count": 0,
            "name": "Trần Tuấn"
        },
        {
            "id": "100050972042794",
            "count": 0,
            "name": "Đặng Thành Đạt"
        },
        {
            "id": "100051245422745",
            "count": 0,
            "name": "Nguyễn Cường"
        },
        {
            "id": "100051317467414",
            "count": 0,
            "name": "Ng Ngoc Truc Linh"
        },
        {
            "id": "100051901751643",
            "count": 0,
            "name": "Hải Trần"
        },
        {
            "id": "100052423595627",
            "count": 0,
            "name": "Hoàng Xướng"
        },
        {
            "id": "100052677201214",
            "count": 0,
            "name": "Nhung Trần"
        },
        {
            "id": "100052914630016",
            "count": 0,
            "name": "Huyền Trâm"
        },
        {
            "id": "100053459353143",
            "count": 0,
            "name": "Oanh Hoàng"
        },
        {
            "id": "100053629447130",
            "count": 0,
            "name": "Phương's Black's"
        },
        {
            "id": "100054661677253",
            "count": 0,
            "name": "Lê Đình Linh"
        },
        {
            "id": "100055314635973",
            "count": 0,
            "name": "Trúc Ly"
        },
        {
            "id": "100055555893056",
            "count": 0,
            "name": "Ngọc Thuận"
        },
        {
            "id": "100055593937770",
            "count": 0,
            "name": "Mei Dayy"
        },
        {
            "id": "100055697006843",
            "count": 0,
            "name": "Hằng Trần"
        },
        {
            "id": "100056866672949",
            "count": 0,
            "name": "Thư Này Cho Bạn"
        },
        {
            "id": "100057134903486",
            "count": 0,
            "name": "N. Ngọc"
        },
        {
            "id": "100058175524214",
            "count": 0,
            "name": "Nguyễn Đạt"
        },
        {
            "id": "100058645046993",
            "count": 0,
            "name": "Khánh Linh"
        },
        {
            "id": "100058842408735",
            "count": 0,
            "name": "이안히"
        },
        {
            "id": "100059682517481",
            "count": 0,
            "name": "Công Trần"
        },
        {
            "id": "100059884234133",
            "count": 0,
            "name": "Tra My"
        },
        {
            "id": "100060430131474",
            "count": 0,
            "name": "Tần Dương"
        },
        {
            "id": "100060936063100",
            "count": 0,
            "name": "Nguyễn Ngọc"
        },
        {
            "id": "100061422077496",
            "count": 0,
            "name": "N.Đ Quỳnh Zy"
        },
        {
            "id": "100062573980288",
            "count": 0,
            "name": "Lâm Tuyết Hoà"
        },
        {
            "id": "100063469263222",
            "count": 0,
            "name": "Yến Phương"
        },
        {
            "id": "100063576116914",
            "count": 0,
            "name": "Ngoc Anh Phạm"
        },
        {
            "id": "100064065200879",
            "count": 0,
            "name": "Ai Thi"
        },
        {
            "id": "100064730705784",
            "count": 0,
            "name": "Tấn Hưng"
        },
        {
            "id": "100064864904115",
            "count": 0,
            "name": "Cẩm Diên"
        },
        {
            "id": "100065333342419",
            "count": 0,
            "name": "Hà Văn Nhất"
        },
        {
            "id": "100066576243307",
            "count": 0,
            "name": "Bình Nguyễn"
        },
        {
            "id": "100068201213552",
            "count": 0,
            "name": "Thanh Hiếu"
        },
        {
            "id": "100068545177109",
            "count": 0,
            "name": "Nguyễn Phương Thảo"
        },
        {
            "id": "100068676198239",
            "count": 0,
            "name": "Đứcc Annh"
        },
        {
            "id": "100068867336823",
            "count": 0,
            "name": "Nam Vũ"
        },
        {
            "id": "100068946031730",
            "count": 0,
            "name": "Hà Tuan Anh"
        },
        {
            "id": "100069756806880",
            "count": 0,
            "name": "Quyền Tatto"
        },
        {
            "id": "100069855820548",
            "count": 0,
            "name": "Nguyễn Dương"
        },
        {
            "id": "100070297303497",
            "count": 0,
            "name": "Khzin Dthw"
        },
        {
            "id": "100070663291260",
            "count": 0,
            "name": "Trọng Nguyễn"
        },
        {
            "id": "100070994245446",
            "count": 0,
            "name": "NT Ngọc Trúc"
        },
        {
            "id": "100071049767402",
            "count": 0,
            "name": "Vân Anh Kiku"
        },
        {
            "id": "100072255319444",
            "count": 0,
            "name": "Thảo Phương Nek"
        },
        {
            "id": "100072257869682",
            "count": 0,
            "name": "Thậtralàtaobịđẹptrai Lạicòncutinữacơý"
        },
        {
            "id": "100072805663375",
            "count": 0,
            "name": "Phuongg Anhh"
        },
        {
            "id": "100073237120661",
            "count": 0,
            "name": "Tao　Vừa　Đẹp　Trai　Vừa　 Cute　Nhất　Vũ　Trụ"
        },
        {
            "id": "100073610085414",
            "count": 0,
            "name": "Nhất ꪜ"
        },
        {
            "id": "100073980825437",
            "count": 0,
            "name": "Chà-xanh- Trộn-matcha"
        },
        {
            "id": "100074037878886",
            "count": 0,
            "name": "Hữu Bằng"
        },
        {
            "id": "100074283784305",
            "count": 0,
            "name": "Đức Annh"
        },
        {
            "id": "100074576227236",
            "count": 0,
            "name": "Phương Võ"
        },
        {
            "id": "100074630951171",
            "count": 0,
            "name": "Nguyễn Thành Trung"
        },
        {
            "id": "100074959639257",
            "count": 0,
            "name": "Trà Đào Cam Xả"
        },
        {
            "id": "100075027864137",
            "count": 0,
            "name": "ʚMinh Túɞ"
        },
        {
            "id": "100076380444403",
            "count": 0,
            "name": "Đặng Văn Quyết"
        },
        {
            "id": "100076507910016",
            "count": 0,
            "name": "Nguyễn'z Quốc'z Bảo'z"
        },
        {
            "id": "100076535876327",
            "count": 0,
            "name": "Thanh Kim"
        },
        {
            "id": "100077080645895",
            "count": 0,
            "name": "Nguyễn Văn Tuấn"
        },
        {
            "id": "100077452946588",
            "count": 0,
            "name": "Doanh Phạm"
        },
        {
            "id": "100077594163249",
            "count": 0,
            "name": "Khánhh Băngg"
        },
        {
            "id": "100078012585693",
            "count": 0,
            "name": "Thư Đoàn"
        },
        {
            "id": "100078205730156",
            "count": 0,
            "name": "Kim Chun"
        },
        {
            "id": "100078442474256",
            "count": 0,
            "name": "Công Xanh Xinh Đẹp"
        },
        {
            "id": "100078681949049",
            "count": 0,
            "name": "Tý Mi Kèn Cố"
        },
        {
            "id": "100079018110551",
            "count": 0,
            "name": "Nguyễn Ánh Thương"
        },
        {
            "id": "100079021664219",
            "count": 0,
            "name": "Ng QuynhNhu"
        },
        {
            "id": "100079071850141",
            "count": 0,
            "name": "Xu KA"
        },
        {
            "id": "100079325465179",
            "count": 0,
            "name": "Han Nhung"
        },
        {
            "id": "100079865631656",
            "count": 0,
            "name": "Thảo Đâyy"
        },
        {
            "id": "100080143350454",
            "count": 0,
            "name": "Trần Văn An"
        },
        {
            "id": "100080506235887",
            "count": 0,
            "name": "Tấnk Hưynq"
        },
        {
            "id": "100080971575866",
            "count": 0,
            "name": "Hiệu Mikenco"
        },
        {
            "id": "100082301112064",
            "count": 0,
            "name": "Lê Tứn"
        },
        {
            "id": "100082589250845",
            "count": 0,
            "name": "Vân Ank"
        },
        {
            "id": "100082684489410",
            "count": 0,
            "name": "Tý Mất Nick"
        },
        {
            "id": "100082709616378",
            "count": 0,
            "name": "Sang Lê"
        },
        {
            "id": "100083258926393",
            "count": 0,
            "name": "Hà Thu"
        },
        {
            "id": "100083853953516",
            "count": 0,
            "name": "Trần Khang"
        },
        {
            "id": "100070914806298",
            "count": 0,
            "name": "ʚThu Trangɞ"
        },
        {
            "id": "100073237527456",
            "count": 0,
            "name": "Phùng Mỹ Duyên"
        }
    ],
    "time": 3
}