{
    "total": [
        {
            "id": "529814191",
            "count": 0
        },
        {
            "id": "628190860",
            "count": 0
        },
        {
            "id": "1203403339",
            "count": 2
        },
        {
            "id": "1216394148",
            "count": 0
        },
        {
            "id": "1377700411",
            "count": 5
        },
        {
            "id": "100000826590692",
            "count": 0
        },
        {
            "id": "100008102416543",
            "count": 0
        },
        {
            "id": "100008780447519",
            "count": 0
        },
        {
            "id": "100012436110684",
            "count": 0
        },
        {
            "id": "100015387725609",
            "count": 0
        },
        {
            "id": "100017686773154",
            "count": 0
        },
        {
            "id": "100019012143607",
            "count": 0
        },
        {
            "id": "100019133275478",
            "count": 11
        },
        {
            "id": "100020266305587",
            "count": 0
        },
        {
            "id": "100022362634825",
            "count": 83
        },
        {
            "id": "100022743826653",
            "count": 0
        },
        {
            "id": "100023076426242",
            "count": 0
        },
        {
            "id": "100023891928947",
            "count": 0
        },
        {
            "id": "100024188851608",
            "count": 0
        },
        {
            "id": "100025330923182",
            "count": 0
        },
        {
            "id": "100025822632196",
            "count": 0
        },
        {
            "id": "100026182453660",
            "count": 0
        },
        {
            "id": "100026500103369",
            "count": 0
        },
        {
            "id": "100026857959991",
            "count": 3
        },
        {
            "id": "100028116097260",
            "count": 0
        },
        {
            "id": "100028247977241",
            "count": 0
        },
        {
            "id": "100028628292764",
            "count": 0
        },
        {
            "id": "100028955088670",
            "count": 0
        },
        {
            "id": "100029197457387",
            "count": 0
        },
        {
            "id": "100029832794650",
            "count": 4
        },
        {
            "id": "100030508262461",
            "count": 0
        },
        {
            "id": "100033747583963",
            "count": 0
        },
        {
            "id": "100035399719928",
            "count": 0
        },
        {
            "id": "100036008523690",
            "count": 0
        },
        {
            "id": "100036700963603",
            "count": 0
        },
        {
            "id": "100036903108421",
            "count": 0
        },
        {
            "id": "100038201160011",
            "count": 50
        },
        {
            "id": "100040221290633",
            "count": 1
        },
        {
            "id": "100040660382366",
            "count": 0
        },
        {
            "id": "100040777215435",
            "count": 0
        },
        {
            "id": "100041148903499",
            "count": 0
        },
        {
            "id": "100042083483299",
            "count": 0
        },
        {
            "id": "100042265613429",
            "count": 1
        },
        {
            "id": "100044287027228",
            "count": 0
        },
        {
            "id": "100044342862411",
            "count": 0
        },
        {
            "id": "100045158176168",
            "count": 0
        },
        {
            "id": "100046246186005",
            "count": 0
        },
        {
            "id": "100047469215026",
            "count": 0
        },
        {
            "id": "100047888492940",
            "count": 0
        },
        {
            "id": "100048303562965",
            "count": 0
        },
        {
            "id": "100049744865230",
            "count": 4
        },
        {
            "id": "100050754132548",
            "count": 0
        },
        {
            "id": "100051374043054",
            "count": 0
        },
        {
            "id": "100051929041810",
            "count": 0
        },
        {
            "id": "100051987949459",
            "count": 0
        },
        {
            "id": "100052740492497",
            "count": 0
        },
        {
            "id": "100053101353336",
            "count": 6
        },
        {
            "id": "100053463500761",
            "count": 2
        },
        {
            "id": "100054557246993",
            "count": 6
        },
        {
            "id": "100055403617754",
            "count": 1
        },
        {
            "id": "100056161865985",
            "count": 0
        },
        {
            "id": "100056229550529",
            "count": 0
        },
        {
            "id": "100057055580301",
            "count": 0
        },
        {
            "id": "100057216767728",
            "count": 0
        },
        {
            "id": "100057836066164",
            "count": 1
        },
        {
            "id": "100057874766289",
            "count": 0
        },
        {
            "id": "100059506456608",
            "count": 0
        },
        {
            "id": "100059690584744",
            "count": 0
        },
        {
            "id": "100060956052792",
            "count": 0
        },
        {
            "id": "100061439136779",
            "count": 0
        },
        {
            "id": "100062924693321",
            "count": 0
        },
        {
            "id": "100063042772274",
            "count": 0
        },
        {
            "id": "100063277082763",
            "count": 1
        },
        {
            "id": "100064101656664",
            "count": 5
        },
        {
            "id": "100064103996638",
            "count": 0
        },
        {
            "id": "100064645186181",
            "count": 0
        },
        {
            "id": "100064730841805",
            "count": 0
        },
        {
            "id": "100065020714461",
            "count": 0
        },
        {
            "id": "100065858491306",
            "count": 0
        },
        {
            "id": "100066579366671",
            "count": 12
        },
        {
            "id": "100066663163191",
            "count": 0
        },
        {
            "id": "100067534184048",
            "count": 0
        },
        {
            "id": "100067535806799",
            "count": 0
        },
        {
            "id": "100067589584158",
            "count": 0
        },
        {
            "id": "100067716173300",
            "count": 1
        },
        {
            "id": "100067800405370",
            "count": 28
        },
        {
            "id": "100069091142817",
            "count": 0
        },
        {
            "id": "100069128116387",
            "count": 0
        },
        {
            "id": "100069147157254",
            "count": 1
        },
        {
            "id": "100069495428719",
            "count": 0
        },
        {
            "id": "100069529901441",
            "count": 3
        },
        {
            "id": "100069613345696",
            "count": 0
        },
        {
            "id": "100069766134148",
            "count": 0
        },
        {
            "id": "100069775382936",
            "count": 0
        },
        {
            "id": "100070186325929",
            "count": 0
        },
        {
            "id": "100071052445586",
            "count": 0
        },
        {
            "id": "100071082186724",
            "count": 0
        },
        {
            "id": "100071424343847",
            "count": 0
        },
        {
            "id": "100071440902420",
            "count": 0
        },
        {
            "id": "100071480711524",
            "count": 0
        },
        {
            "id": "100071948716105",
            "count": 0
        },
        {
            "id": "100072770431252",
            "count": 8
        },
        {
            "id": "100072774799280",
            "count": 6
        },
        {
            "id": "100072849884165",
            "count": 1
        },
        {
            "id": "100073333820887",
            "count": 3
        },
        {
            "id": "100073715171739",
            "count": 0
        },
        {
            "id": "100073737870131",
            "count": 55
        },
        {
            "id": "100073746062744",
            "count": 0
        },
        {
            "id": "100074053633515",
            "count": 0
        },
        {
            "id": "100074277403285",
            "count": 3
        },
        {
            "id": "100074441246742",
            "count": 0
        },
        {
            "id": "100074604466001",
            "count": 0
        },
        {
            "id": "100074646828002",
            "count": 7
        },
        {
            "id": "100074819287667",
            "count": 0
        },
        {
            "id": "100074965307796",
            "count": 1
        },
        {
            "id": "100075081714064",
            "count": 0
        },
        {
            "id": "100075139694936",
            "count": 0
        },
        {
            "id": "100075690761634",
            "count": 4
        },
        {
            "id": "100076065715348",
            "count": 0
        },
        {
            "id": "100076558531414",
            "count": 0
        },
        {
            "id": "100076580416328",
            "count": 0
        },
        {
            "id": "100076846692126",
            "count": 0
        },
        {
            "id": "100077834770956",
            "count": 0
        },
        {
            "id": "100077906661531",
            "count": 0
        },
        {
            "id": "100078211835575",
            "count": 0
        },
        {
            "id": "100078363426309",
            "count": 0
        },
        {
            "id": "100078758942716",
            "count": 0
        },
        {
            "id": "100078793545811",
            "count": 0
        },
        {
            "id": "100080374197878",
            "count": 0
        },
        {
            "id": "100080641233955",
            "count": 0
        },
        {
            "id": "100081052805795",
            "count": 0
        },
        {
            "id": "100081105078380",
            "count": 0
        },
        {
            "id": "100081410632098",
            "count": 0
        },
        {
            "id": "100081522223945",
            "count": 0
        },
        {
            "id": "100081563002849",
            "count": 0
        },
        {
            "id": "100081708717952",
            "count": 2
        },
        {
            "id": "100081831939704",
            "count": 0
        },
        {
            "id": "100081942060472",
            "count": 1
        },
        {
            "id": "100081997543021",
            "count": 0
        },
        {
            "id": "100082224344933",
            "count": 6
        },
        {
            "id": "100082301112064",
            "count": 52
        },
        {
            "id": "100082317462275",
            "count": 0
        },
        {
            "id": "100082372722267",
            "count": 0
        },
        {
            "id": "100082943172861",
            "count": 0
        },
        {
            "id": "100083201202585",
            "count": 0
        },
        {
            "id": "100083315834901",
            "count": 1
        },
        {
            "id": "100083497784241",
            "count": 2
        },
        {
            "id": "100083554760631",
            "count": 0
        },
        {
            "id": "100083714915921",
            "count": 0
        },
        {
            "id": "100083819503058",
            "count": 0
        },
        {
            "id": "100084116224382",
            "count": 0
        },
        {
            "id": "100077179487506",
            "count": 2
        },
        {
            "id": "100051932492970",
            "count": 14
        },
        {
            "id": "100073307092666",
            "count": 32
        },
        {
            "id": "100045694145946",
            "count": 5
        }
    ],
    "week": [
        {
            "id": "529814191",
            "count": 0,
            "name": "Nguyễn Hoàng Duy Tiến"
        },
        {
            "id": "628190860",
            "count": 0,
            "name": "Người dùng Facebook"
        },
        {
            "id": "1203403339",
            "count": 0,
            "name": "Cam Xả Chua Ngọt"
        },
        {
            "id": "1216394148",
            "count": 0,
            "name": "Dương Gia Long"
        },
        {
            "id": "1377700411",
            "count": 0,
            "name": "Minh Tuấn Nông"
        },
        {
            "id": "100000826590692",
            "count": 0,
            "name": "️️️️️️️️️️️️️️️️️️️️️️️️️️️️️️️️️️️️️️️️️️️️️️️️️️️️️️️️️️️️️️️️️️️️️️️️️️️️️️️️️️️️️️️️️️️️️️️️️️️️️️️️️️️️️️️️️️️️️️️️️️️️️️️️️️️️️️️️️️️️️️️️️️️️️️️️️️️️️️️️️️️️️️️️️️"
        },
        {
            "id": "100008102416543",
            "count": 0,
            "name": "Trần Minh"
        },
        {
            "id": "100008780447519",
            "count": 0,
            "name": "Nguyen Long Dat"
        },
        {
            "id": "100012436110684",
            "count": 0,
            "name": "Sơn Minh Đức"
        },
        {
            "id": "100015387725609",
            "count": 0,
            "name": "Mai Thanh Huyền"
        },
        {
            "id": "100017686773154",
            "count": 0,
            "name": "Người dùng Facebook"
        },
        {
            "id": "100019012143607",
            "count": 0,
            "name": "Nguyen Ng Chau Anh"
        },
        {
            "id": "100019133275478",
            "count": 0,
            "name": "Tr Quoc Bao"
        },
        {
            "id": "100020266305587",
            "count": 0,
            "name": "Bảo Hân"
        },
        {
            "id": "100022362634825",
            "count": 0,
            "name": "Nước Mắt Anh Rơi Trò Chơi Miễn Phí Anh Sơn Vũ Khí Tiếp Tục Trò Chơi Gió Đưa Cành Trúc La Đà Súng Mà Chưa Mạnh Chắc Là Chưa Sơn Trước Chùa Mưa Rơi Nhạc Giật Hồi Máu Nhạc Giật Bay Bay Máu Anh Đã Đầy Gọi Anh Là Cháu Anh Học Mầm Non Gọi Anh Là Con Tiểu Học Năm Nhất Ông Già Anh Mất Bà Già Anh Thăng Suốt Ngày Lăng Nhăng Anh Đây Vẫn Chất 𓅃"
        },
        {
            "id": "100022743826653",
            "count": 0,
            "name": "Trọng Nhân"
        },
        {
            "id": "100023076426242",
            "count": 0,
            "name": "Tống Hoàng Minh Quân"
        },
        {
            "id": "100023891928947",
            "count": 0,
            "name": "Tr Gia Nghi"
        },
        {
            "id": "100024188851608",
            "count": 0,
            "name": "Trà Thị Nguyên"
        },
        {
            "id": "100025330923182",
            "count": 0,
            "name": "Nguyễn Hữu Phúc"
        },
        {
            "id": "100025822632196",
            "count": 0,
            "name": "Tấn Tài"
        },
        {
            "id": "100026182453660",
            "count": 0,
            "name": "Nguyễn Tâm An"
        },
        {
            "id": "100026500103369",
            "count": 0,
            "name": "Duc Duy"
        },
        {
            "id": "100026857959991",
            "count": 0,
            "name": "Xuân Mai"
        },
        {
            "id": "100028116097260",
            "count": 0,
            "name": "Kim Ngân"
        },
        {
            "id": "100028247977241",
            "count": 0,
            "name": "Thư Đoàn"
        },
        {
            "id": "100028628292764",
            "count": 0,
            "name": "Minh Longg"
        },
        {
            "id": "100028955088670",
            "count": 0,
            "name": "Nguyen Huu Toan"
        },
        {
            "id": "100029197457387",
            "count": 0,
            "name": "NGUYỄN VĂN NHÂN"
        },
        {
            "id": "100029832794650",
            "count": 0,
            "name": "Phạm Bảo"
        },
        {
            "id": "100030508262461",
            "count": 0,
            "name": "Thanh Duy"
        },
        {
            "id": "100033747583963",
            "count": 0,
            "name": "Phan Thái Nguyên"
        },
        {
            "id": "100035399719928",
            "count": 0,
            "name": "Trần Đức Phúc Hậu"
        },
        {
            "id": "100036008523690",
            "count": 0,
            "name": "Hoang Mai Anh"
        },
        {
            "id": "100036700963603",
            "count": 0,
            "name": "Trần Hà Bảo Di"
        },
        {
            "id": "100036903108421",
            "count": 0,
            "name": "Nguyễn Diệu Linh"
        },
        {
            "id": "100038201160011",
            "count": 0,
            "name": "Thiênn Thư"
        },
        {
            "id": "100040221290633",
            "count": 0,
            "name": "Đinh Thị Hải Ngân"
        },
        {
            "id": "100040660382366",
            "count": 0,
            "name": "Trung Kiệt"
        },
        {
            "id": "100040777215435",
            "count": 0,
            "name": "Trần Lam"
        },
        {
            "id": "100041148903499",
            "count": 0,
            "name": "Nguyễn Hoài Nam"
        },
        {
            "id": "100042083483299",
            "count": 0,
            "name": "Trà My"
        },
        {
            "id": "100042265613429",
            "count": 0,
            "name": "Đặng Công Tảo"
        },
        {
            "id": "100044287027228",
            "count": 0,
            "name": "Hiệp Hoàn"
        },
        {
            "id": "100044342862411",
            "count": 0,
            "name": "Ngoc Khoi"
        },
        {
            "id": "100045158176168",
            "count": 0,
            "name": "Tên Nguyen Anh"
        },
        {
            "id": "100046246186005",
            "count": 0,
            "name": "Nguyen Quynh"
        },
        {
            "id": "100047469215026",
            "count": 0,
            "name": "Phạm Đạt"
        },
        {
            "id": "100047888492940",
            "count": 0,
            "name": "Trần Quốc Hòa"
        },
        {
            "id": "100048303562965",
            "count": 0,
            "name": "Tr Nguyễn Khánh Linh"
        },
        {
            "id": "100049744865230",
            "count": 0,
            "name": "Nguyễn Mạnh Hùng"
        },
        {
            "id": "100050754132548",
            "count": 0,
            "name": "Khánh Ngọc"
        },
        {
            "id": "100051374043054",
            "count": 0,
            "name": "Nam Truong"
        },
        {
            "id": "100051929041810",
            "count": 0,
            "name": "Huy Hoàng"
        },
        {
            "id": "100051987949459",
            "count": 0,
            "name": "Mỹ Khang"
        },
        {
            "id": "100052740492497",
            "count": 0,
            "name": "Tr DangKhoa"
        },
        {
            "id": "100053101353336",
            "count": 0,
            "name": "Vann Huyy"
        },
        {
            "id": "100053463500761",
            "count": 0,
            "name": "Thanh Thảo"
        },
        {
            "id": "100054557246993",
            "count": 0,
            "name": "LV Hoàng"
        },
        {
            "id": "100055403617754",
            "count": 0,
            "name": "ۦۦۦۦ ۦۦ ۦۦۦۦ ۦۦ"
        },
        {
            "id": "100056161865985",
            "count": 0,
            "name": "Phương Thảo"
        },
        {
            "id": "100056229550529",
            "count": 0,
            "name": "Quỳnh Như"
        },
        {
            "id": "100057055580301",
            "count": 0,
            "name": "Nguyễn Đỗ Đình Đăng"
        },
        {
            "id": "100057216767728",
            "count": 0,
            "name": "Ng Thuy Duong"
        },
        {
            "id": "100057836066164",
            "count": 0,
            "name": "Ng Nhi"
        },
        {
            "id": "100057874766289",
            "count": 0,
            "name": "Nhu Ngocc"
        },
        {
            "id": "100059506456608",
            "count": 0,
            "name": "NQ Hải"
        },
        {
            "id": "100059690584744",
            "count": 0,
            "name": "Người dùng Facebook"
        },
        {
            "id": "100060956052792",
            "count": 0,
            "name": "Gia Mỹ"
        },
        {
            "id": "100061439136779",
            "count": 0,
            "name": "Huyền Trang"
        },
        {
            "id": "100062924693321",
            "count": 0,
            "name": "Quynhh Anhh"
        },
        {
            "id": "100063042772274",
            "count": 0,
            "name": "Nhật Thiện"
        },
        {
            "id": "100063277082763",
            "count": 0,
            "name": "Bích Ngà"
        },
        {
            "id": "100064101656664",
            "count": 0,
            "name": "Lê Sơn"
        },
        {
            "id": "100064103996638",
            "count": 0,
            "name": "Tấn Khang"
        },
        {
            "id": "100064645186181",
            "count": 0,
            "name": "Tr Giaa Vy"
        },
        {
            "id": "100064730841805",
            "count": 0,
            "name": "Huỳnh Hà Vy"
        },
        {
            "id": "100065020714461",
            "count": 0,
            "name": "Phan Thị Thu Ngân"
        },
        {
            "id": "100065858491306",
            "count": 0,
            "name": "Le T. Phong"
        },
        {
            "id": "100066579366671",
            "count": 0,
            "name": "Hồ Quốc"
        },
        {
            "id": "100066663163191",
            "count": 0,
            "name": "Bùi Thị Hồng Liên"
        },
        {
            "id": "100067534184048",
            "count": 0,
            "name": "Nguyễn Minh Anh"
        },
        {
            "id": "100067535806799",
            "count": 0,
            "name": "Cao Thai Nhien"
        },
        {
            "id": "100067589584158",
            "count": 0,
            "name": "Thúy Nguyễn"
        },
        {
            "id": "100067716173300",
            "count": 0,
            "name": "Cu Chiến"
        },
        {
            "id": "100067800405370",
            "count": 0,
            "name": "Kim Anh"
        },
        {
            "id": "100069091142817",
            "count": 0,
            "name": "Anh Tuan"
        },
        {
            "id": "100069128116387",
            "count": 0,
            "name": "Lê Xuân Anh"
        },
        {
            "id": "100069147157254",
            "count": 0,
            "name": "Quoc Ân"
        },
        {
            "id": "100069495428719",
            "count": 0,
            "name": "𝑳𝒆̂ 𝑻𝒉𝒂̉𝒐𝒐 𝑽𝒚𝒚"
        },
        {
            "id": "100069529901441",
            "count": 0,
            "name": "Hà Khánh Hưng"
        },
        {
            "id": "100069613345696",
            "count": 0,
            "name": "Tran Thu Le"
        },
        {
            "id": "100069766134148",
            "count": 0,
            "name": "Ng Truc Nhu"
        },
        {
            "id": "100069775382936",
            "count": 0,
            "name": "Người dùng Facebook"
        },
        {
            "id": "100070186325929",
            "count": 0,
            "name": "Gia Phong"
        },
        {
            "id": "100071052445586",
            "count": 0,
            "name": "Bảo Khanh"
        },
        {
            "id": "100071082186724",
            "count": 0,
            "name": "Người dùng Facebook"
        },
        {
            "id": "100071424343847",
            "count": 0,
            "name": "Kiều Ngọc Nhi"
        },
        {
            "id": "100071440902420",
            "count": 0,
            "name": "Thanh Trà"
        },
        {
            "id": "100071480711524",
            "count": 0,
            "name": "Tr Duy Anh"
        },
        {
            "id": "100071948716105",
            "count": 0,
            "name": "Kim Anh"
        },
        {
            "id": "100072770431252",
            "count": 0,
            "name": "Nguyễn Văn Thoan"
        },
        {
            "id": "100072774799280",
            "count": 0,
            "name": "Hứa Nguyệt Ly"
        },
        {
            "id": "100072849884165",
            "count": 0,
            "name": "Ngọc Diễm"
        },
        {
            "id": "100073333820887",
            "count": 0,
            "name": "Linh Chi"
        },
        {
            "id": "100073715171739",
            "count": 0,
            "name": "Dan Anhh"
        },
        {
            "id": "100073737870131",
            "count": 0,
            "name": "Ng Nha Ky"
        },
        {
            "id": "100073746062744",
            "count": 0,
            "name": "Văn Hiếuu"
        },
        {
            "id": "100074053633515",
            "count": 0,
            "name": "Minh Tuấnn"
        },
        {
            "id": "100074277403285",
            "count": 0,
            "name": "Quynh Nhu CT"
        },
        {
            "id": "100074441246742",
            "count": 0,
            "name": "Ph Thi Kim Ngan"
        },
        {
            "id": "100074604466001",
            "count": 0,
            "name": "Nguyễn Phi Hoàng"
        },
        {
            "id": "100074646828002",
            "count": 0,
            "name": "NgNg Kieu Oanh"
        },
        {
            "id": "100074819287667",
            "count": 0,
            "name": "Viet Anh"
        },
        {
            "id": "100074965307796",
            "count": 0,
            "name": "Tr Nhân"
        },
        {
            "id": "100075081714064",
            "count": 0,
            "name": "N Ng Gia Han"
        },
        {
            "id": "100075139694936",
            "count": 0,
            "name": "Thanh Tú"
        },
        {
            "id": "100075690761634",
            "count": 0,
            "name": "Hoàng Đỗ"
        },
        {
            "id": "100076065715348",
            "count": 0,
            "name": "Trọng Hiếu"
        },
        {
            "id": "100076558531414",
            "count": 0,
            "name": "Hoàng Aanh"
        },
        {
            "id": "100076580416328",
            "count": 0,
            "name": "Trương Ngọc Hạ My"
        },
        {
            "id": "100076846692126",
            "count": 0,
            "name": "LE Nguyen Khang JW"
        },
        {
            "id": "100077834770956",
            "count": 0,
            "name": "Nguyễn Quốc Tuấn"
        },
        {
            "id": "100077906661531",
            "count": 0,
            "name": "Trung Hiếu"
        },
        {
            "id": "100078211835575",
            "count": 0,
            "name": "Người dùng Facebook"
        },
        {
            "id": "100078363426309",
            "count": 0,
            "name": "Hoàng Dương"
        },
        {
            "id": "100078758942716",
            "count": 0,
            "name": "Phạm Tuấn"
        },
        {
            "id": "100078793545811",
            "count": 0,
            "name": "Hồng Cẩm"
        },
        {
            "id": "100080374197878",
            "count": 0,
            "name": "Văn Hiếu"
        },
        {
            "id": "100080641233955",
            "count": 0,
            "name": "Tr Uyen Nhii"
        },
        {
            "id": "100081052805795",
            "count": 0,
            "name": "Bảo Nhi"
        },
        {
            "id": "100081105078380",
            "count": 0,
            "name": "Tran Cong Minh"
        },
        {
            "id": "100081410632098",
            "count": 0,
            "name": "Hoàng Nghĩa"
        },
        {
            "id": "100081522223945",
            "count": 0,
            "name": "Tr Ngoc Gia Nghi M.M"
        },
        {
            "id": "100081563002849",
            "count": 0,
            "name": "Lê Hữu Tài"
        },
        {
            "id": "100081708717952",
            "count": 0,
            "name": "Trác Kmeo"
        },
        {
            "id": "100081831939704",
            "count": 0,
            "name": "Nguyễn Hoàng Ngọc Nhi"
        },
        {
            "id": "100081942060472",
            "count": 0,
            "name": "Vũ Mạnh Tuấn"
        },
        {
            "id": "100081997543021",
            "count": 0,
            "name": "Người dùng Facebook"
        },
        {
            "id": "100082224344933",
            "count": 0,
            "name": "Quang Đạt"
        },
        {
            "id": "100082301112064",
            "count": 0,
            "name": "Lê Tứn"
        },
        {
            "id": "100082317462275",
            "count": 0,
            "name": "Ng Tuấn"
        },
        {
            "id": "100082372722267",
            "count": 0,
            "name": "Mạnh Cườngg"
        },
        {
            "id": "100082943172861",
            "count": 0,
            "name": "Hoàng Aanh"
        },
        {
            "id": "100083201202585",
            "count": 0,
            "name": "Kem Trứng Muối"
        },
        {
            "id": "100083315834901",
            "count": 0,
            "name": "Trần Trọng Tín"
        },
        {
            "id": "100083497784241",
            "count": 0,
            "name": "Tr Ng Đăng Khoa"
        },
        {
            "id": "100083554760631",
            "count": 0,
            "name": "Như Huỳnh"
        },
        {
            "id": "100083714915921",
            "count": 0,
            "name": "NT Thanh Hoa"
        },
        {
            "id": "100083819503058",
            "count": 0,
            "name": "Dinh Thi Hai Ngan"
        },
        {
            "id": "100084116224382",
            "count": 0,
            "name": "Ng Anh Duc"
        },
        {
            "id": "100077179487506",
            "count": 0,
            "name": "Mai Ng Xuân Anh"
        },
        {
            "id": "100051932492970",
            "count": 0,
            "name": "Hoàng V Sang"
        },
        {
            "id": "100073307092666",
            "count": 0,
            "name": "Trà Mi"
        },
        {
            "id": "100045694145946",
            "count": 0,
            "name": "Thao Nhi"
        }
    ],
    "day": [
        {
            "id": "529814191",
            "count": 0,
            "name": "Nguyễn Hoàng Duy Tiến"
        },
        {
            "id": "628190860",
            "count": 0,
            "name": "Người dùng Facebook"
        },
        {
            "id": "1203403339",
            "count": 0,
            "name": "Cam Xả Chua Ngọt"
        },
        {
            "id": "1216394148",
            "count": 0,
            "name": "Dương Gia Long"
        },
        {
            "id": "1377700411",
            "count": 0,
            "name": "Minh Tuấn Nông"
        },
        {
            "id": "100000826590692",
            "count": 0,
            "name": "️️️️️️️️️️️️️️️️️️️️️️️️️️️️️️️️️️️️️️️️️️️️️️️️️️️️️️️️️️️️️️️️️️️️️️️️️️️️️️️️️️️️️️️️️️️️️️️️️️️️️️️️️️️️️️️️️️️️️️️️️️️️️️️️️️️️️️️️️️️️️️️️️️️️️️️️️️️️️️️️️️️️️️️️️️"
        },
        {
            "id": "100008102416543",
            "count": 0,
            "name": "Trần Minh"
        },
        {
            "id": "100008780447519",
            "count": 0,
            "name": "Nguyen Long Dat"
        },
        {
            "id": "100012436110684",
            "count": 0,
            "name": "Sơn Minh Đức"
        },
        {
            "id": "100015387725609",
            "count": 0,
            "name": "Mai Thanh Huyền"
        },
        {
            "id": "100017686773154",
            "count": 0,
            "name": "Người dùng Facebook"
        },
        {
            "id": "100019012143607",
            "count": 0,
            "name": "Nguyen Ng Chau Anh"
        },
        {
            "id": "100019133275478",
            "count": 0,
            "name": "Tr Quoc Bao"
        },
        {
            "id": "100020266305587",
            "count": 0,
            "name": "Bảo Hân"
        },
        {
            "id": "100022362634825",
            "count": 0,
            "name": "Nước Mắt Anh Rơi Trò Chơi Miễn Phí Anh Sơn Vũ Khí Tiếp Tục Trò Chơi Gió Đưa Cành Trúc La Đà Súng Mà Chưa Mạnh Chắc Là Chưa Sơn Trước Chùa Mưa Rơi Nhạc Giật Hồi Máu Nhạc Giật Bay Bay Máu Anh Đã Đầy Gọi Anh Là Cháu Anh Học Mầm Non Gọi Anh Là Con Tiểu Học Năm Nhất Ông Già Anh Mất Bà Già Anh Thăng Suốt Ngày Lăng Nhăng Anh Đây Vẫn Chất 𓅃"
        },
        {
            "id": "100022743826653",
            "count": 0,
            "name": "Trọng Nhân"
        },
        {
            "id": "100023076426242",
            "count": 0,
            "name": "Tống Hoàng Minh Quân"
        },
        {
            "id": "100023891928947",
            "count": 0,
            "name": "Tr Gia Nghi"
        },
        {
            "id": "100024188851608",
            "count": 0,
            "name": "Trà Thị Nguyên"
        },
        {
            "id": "100025330923182",
            "count": 0,
            "name": "Nguyễn Hữu Phúc"
        },
        {
            "id": "100025822632196",
            "count": 0,
            "name": "Tấn Tài"
        },
        {
            "id": "100026182453660",
            "count": 0,
            "name": "Nguyễn Tâm An"
        },
        {
            "id": "100026500103369",
            "count": 0,
            "name": "Duc Duy"
        },
        {
            "id": "100026857959991",
            "count": 0,
            "name": "Xuân Mai"
        },
        {
            "id": "100028116097260",
            "count": 0,
            "name": "Kim Ngân"
        },
        {
            "id": "100028247977241",
            "count": 0,
            "name": "Thư Đoàn"
        },
        {
            "id": "100028628292764",
            "count": 0,
            "name": "Minh Longg"
        },
        {
            "id": "100028955088670",
            "count": 0,
            "name": "Nguyen Huu Toan"
        },
        {
            "id": "100029197457387",
            "count": 0,
            "name": "NGUYỄN VĂN NHÂN"
        },
        {
            "id": "100029832794650",
            "count": 0,
            "name": "Phạm Bảo"
        },
        {
            "id": "100030508262461",
            "count": 0,
            "name": "Thanh Duy"
        },
        {
            "id": "100033747583963",
            "count": 0,
            "name": "Phan Thái Nguyên"
        },
        {
            "id": "100035399719928",
            "count": 0,
            "name": "Trần Đức Phúc Hậu"
        },
        {
            "id": "100036008523690",
            "count": 0,
            "name": "Hoang Mai Anh"
        },
        {
            "id": "100036700963603",
            "count": 0,
            "name": "Trần Hà Bảo Di"
        },
        {
            "id": "100036903108421",
            "count": 0,
            "name": "Nguyễn Diệu Linh"
        },
        {
            "id": "100038201160011",
            "count": 0,
            "name": "Thiênn Thư"
        },
        {
            "id": "100040221290633",
            "count": 0,
            "name": "Đinh Thị Hải Ngân"
        },
        {
            "id": "100040660382366",
            "count": 0,
            "name": "Trung Kiệt"
        },
        {
            "id": "100040777215435",
            "count": 0,
            "name": "Trần Lam"
        },
        {
            "id": "100041148903499",
            "count": 0,
            "name": "Nguyễn Hoài Nam"
        },
        {
            "id": "100042083483299",
            "count": 0,
            "name": "Trà My"
        },
        {
            "id": "100042265613429",
            "count": 0,
            "name": "Đặng Công Tảo"
        },
        {
            "id": "100044287027228",
            "count": 0,
            "name": "Hiệp Hoàn"
        },
        {
            "id": "100044342862411",
            "count": 0,
            "name": "Ngoc Khoi"
        },
        {
            "id": "100045158176168",
            "count": 0,
            "name": "Tên Nguyen Anh"
        },
        {
            "id": "100046246186005",
            "count": 0,
            "name": "Nguyen Quynh"
        },
        {
            "id": "100047469215026",
            "count": 0,
            "name": "Phạm Đạt"
        },
        {
            "id": "100047888492940",
            "count": 0,
            "name": "Trần Quốc Hòa"
        },
        {
            "id": "100048303562965",
            "count": 0,
            "name": "Tr Nguyễn Khánh Linh"
        },
        {
            "id": "100049744865230",
            "count": 0,
            "name": "Nguyễn Mạnh Hùng"
        },
        {
            "id": "100050754132548",
            "count": 0,
            "name": "Khánh Ngọc"
        },
        {
            "id": "100051374043054",
            "count": 0,
            "name": "Nam Truong"
        },
        {
            "id": "100051929041810",
            "count": 0,
            "name": "Huy Hoàng"
        },
        {
            "id": "100051987949459",
            "count": 0,
            "name": "Mỹ Khang"
        },
        {
            "id": "100052740492497",
            "count": 0,
            "name": "Tr DangKhoa"
        },
        {
            "id": "100053101353336",
            "count": 0,
            "name": "Vann Huyy"
        },
        {
            "id": "100053463500761",
            "count": 0,
            "name": "Thanh Thảo"
        },
        {
            "id": "100054557246993",
            "count": 0,
            "name": "LV Hoàng"
        },
        {
            "id": "100055403617754",
            "count": 0,
            "name": "ۦۦۦۦ ۦۦ ۦۦۦۦ ۦۦ"
        },
        {
            "id": "100056161865985",
            "count": 0,
            "name": "Phương Thảo"
        },
        {
            "id": "100056229550529",
            "count": 0,
            "name": "Quỳnh Như"
        },
        {
            "id": "100057055580301",
            "count": 0,
            "name": "Nguyễn Đỗ Đình Đăng"
        },
        {
            "id": "100057216767728",
            "count": 0,
            "name": "Ng Thuy Duong"
        },
        {
            "id": "100057836066164",
            "count": 0,
            "name": "Ng Nhi"
        },
        {
            "id": "100057874766289",
            "count": 0,
            "name": "Nhu Ngocc"
        },
        {
            "id": "100059506456608",
            "count": 0,
            "name": "NQ Hải"
        },
        {
            "id": "100059690584744",
            "count": 0,
            "name": "Người dùng Facebook"
        },
        {
            "id": "100060956052792",
            "count": 0,
            "name": "Gia Mỹ"
        },
        {
            "id": "100061439136779",
            "count": 0,
            "name": "Huyền Trang"
        },
        {
            "id": "100062924693321",
            "count": 0,
            "name": "Quynhh Anhh"
        },
        {
            "id": "100063042772274",
            "count": 0,
            "name": "Nhật Thiện"
        },
        {
            "id": "100063277082763",
            "count": 0,
            "name": "Bích Ngà"
        },
        {
            "id": "100064101656664",
            "count": 0,
            "name": "Lê Sơn"
        },
        {
            "id": "100064103996638",
            "count": 0,
            "name": "Tấn Khang"
        },
        {
            "id": "100064645186181",
            "count": 0,
            "name": "Tr Giaa Vy"
        },
        {
            "id": "100064730841805",
            "count": 0,
            "name": "Huỳnh Hà Vy"
        },
        {
            "id": "100065020714461",
            "count": 0,
            "name": "Phan Thị Thu Ngân"
        },
        {
            "id": "100065858491306",
            "count": 0,
            "name": "Le T. Phong"
        },
        {
            "id": "100066579366671",
            "count": 0,
            "name": "Hồ Quốc"
        },
        {
            "id": "100066663163191",
            "count": 0,
            "name": "Bùi Thị Hồng Liên"
        },
        {
            "id": "100067534184048",
            "count": 0,
            "name": "Nguyễn Minh Anh"
        },
        {
            "id": "100067535806799",
            "count": 0,
            "name": "Cao Thai Nhien"
        },
        {
            "id": "100067589584158",
            "count": 0,
            "name": "Thúy Nguyễn"
        },
        {
            "id": "100067716173300",
            "count": 0,
            "name": "Cu Chiến"
        },
        {
            "id": "100067800405370",
            "count": 0,
            "name": "Kim Anh"
        },
        {
            "id": "100069091142817",
            "count": 0,
            "name": "Anh Tuan"
        },
        {
            "id": "100069128116387",
            "count": 0,
            "name": "Lê Xuân Anh"
        },
        {
            "id": "100069147157254",
            "count": 0,
            "name": "Quoc Ân"
        },
        {
            "id": "100069495428719",
            "count": 0,
            "name": "𝑳𝒆̂ 𝑻𝒉𝒂̉𝒐𝒐 𝑽𝒚𝒚"
        },
        {
            "id": "100069529901441",
            "count": 0,
            "name": "Hà Khánh Hưng"
        },
        {
            "id": "100069613345696",
            "count": 0,
            "name": "Tran Thu Le"
        },
        {
            "id": "100069766134148",
            "count": 0,
            "name": "Ng Truc Nhu"
        },
        {
            "id": "100069775382936",
            "count": 0,
            "name": "Người dùng Facebook"
        },
        {
            "id": "100070186325929",
            "count": 0,
            "name": "Gia Phong"
        },
        {
            "id": "100071052445586",
            "count": 0,
            "name": "Bảo Khanh"
        },
        {
            "id": "100071082186724",
            "count": 0,
            "name": "Người dùng Facebook"
        },
        {
            "id": "100071424343847",
            "count": 0,
            "name": "Kiều Ngọc Nhi"
        },
        {
            "id": "100071440902420",
            "count": 0,
            "name": "Thanh Trà"
        },
        {
            "id": "100071480711524",
            "count": 0,
            "name": "Tr Duy Anh"
        },
        {
            "id": "100071948716105",
            "count": 0,
            "name": "Kim Anh"
        },
        {
            "id": "100072770431252",
            "count": 0,
            "name": "Nguyễn Văn Thoan"
        },
        {
            "id": "100072774799280",
            "count": 0,
            "name": "Hứa Nguyệt Ly"
        },
        {
            "id": "100072849884165",
            "count": 0,
            "name": "Ngọc Diễm"
        },
        {
            "id": "100073333820887",
            "count": 0,
            "name": "Linh Chi"
        },
        {
            "id": "100073715171739",
            "count": 0,
            "name": "Dan Anhh"
        },
        {
            "id": "100073737870131",
            "count": 0,
            "name": "Ng Nha Ky"
        },
        {
            "id": "100073746062744",
            "count": 0,
            "name": "Văn Hiếuu"
        },
        {
            "id": "100074053633515",
            "count": 0,
            "name": "Minh Tuấnn"
        },
        {
            "id": "100074277403285",
            "count": 0,
            "name": "Quynh Nhu CT"
        },
        {
            "id": "100074441246742",
            "count": 0,
            "name": "Ph Thi Kim Ngan"
        },
        {
            "id": "100074604466001",
            "count": 0,
            "name": "Nguyễn Phi Hoàng"
        },
        {
            "id": "100074646828002",
            "count": 0,
            "name": "NgNg Kieu Oanh"
        },
        {
            "id": "100074819287667",
            "count": 0,
            "name": "Viet Anh"
        },
        {
            "id": "100074965307796",
            "count": 0,
            "name": "Tr Nhân"
        },
        {
            "id": "100075081714064",
            "count": 0,
            "name": "N Ng Gia Han"
        },
        {
            "id": "100075139694936",
            "count": 0,
            "name": "Thanh Tú"
        },
        {
            "id": "100075690761634",
            "count": 0,
            "name": "Hoàng Đỗ"
        },
        {
            "id": "100076065715348",
            "count": 0,
            "name": "Trọng Hiếu"
        },
        {
            "id": "100076558531414",
            "count": 0,
            "name": "Hoàng Aanh"
        },
        {
            "id": "100076580416328",
            "count": 0,
            "name": "Trương Ngọc Hạ My"
        },
        {
            "id": "100076846692126",
            "count": 0,
            "name": "LE Nguyen Khang JW"
        },
        {
            "id": "100077834770956",
            "count": 0,
            "name": "Nguyễn Quốc Tuấn"
        },
        {
            "id": "100077906661531",
            "count": 0,
            "name": "Trung Hiếu"
        },
        {
            "id": "100078211835575",
            "count": 0,
            "name": "Người dùng Facebook"
        },
        {
            "id": "100078363426309",
            "count": 0,
            "name": "Hoàng Dương"
        },
        {
            "id": "100078758942716",
            "count": 0,
            "name": "Phạm Tuấn"
        },
        {
            "id": "100078793545811",
            "count": 0,
            "name": "Hồng Cẩm"
        },
        {
            "id": "100080374197878",
            "count": 0,
            "name": "Văn Hiếu"
        },
        {
            "id": "100080641233955",
            "count": 0,
            "name": "Tr Uyen Nhii"
        },
        {
            "id": "100081052805795",
            "count": 0,
            "name": "Bảo Nhi"
        },
        {
            "id": "100081105078380",
            "count": 0,
            "name": "Tran Cong Minh"
        },
        {
            "id": "100081410632098",
            "count": 0,
            "name": "Hoàng Nghĩa"
        },
        {
            "id": "100081522223945",
            "count": 0,
            "name": "Tr Ngoc Gia Nghi M.M"
        },
        {
            "id": "100081563002849",
            "count": 0,
            "name": "Lê Hữu Tài"
        },
        {
            "id": "100081708717952",
            "count": 0,
            "name": "Trác Kmeo"
        },
        {
            "id": "100081831939704",
            "count": 0,
            "name": "Nguyễn Hoàng Ngọc Nhi"
        },
        {
            "id": "100081942060472",
            "count": 0,
            "name": "Vũ Mạnh Tuấn"
        },
        {
            "id": "100081997543021",
            "count": 0,
            "name": "Người dùng Facebook"
        },
        {
            "id": "100082224344933",
            "count": 0,
            "name": "Quang Đạt"
        },
        {
            "id": "100082301112064",
            "count": 0,
            "name": "Lê Tứn"
        },
        {
            "id": "100082317462275",
            "count": 0,
            "name": "Ng Tuấn"
        },
        {
            "id": "100082372722267",
            "count": 0,
            "name": "Mạnh Cườngg"
        },
        {
            "id": "100082943172861",
            "count": 0,
            "name": "Hoàng Aanh"
        },
        {
            "id": "100083201202585",
            "count": 0,
            "name": "Kem Trứng Muối"
        },
        {
            "id": "100083315834901",
            "count": 0,
            "name": "Trần Trọng Tín"
        },
        {
            "id": "100083497784241",
            "count": 0,
            "name": "Tr Ng Đăng Khoa"
        },
        {
            "id": "100083554760631",
            "count": 0,
            "name": "Như Huỳnh"
        },
        {
            "id": "100083714915921",
            "count": 0,
            "name": "NT Thanh Hoa"
        },
        {
            "id": "100083819503058",
            "count": 0,
            "name": "Dinh Thi Hai Ngan"
        },
        {
            "id": "100084116224382",
            "count": 0,
            "name": "Ng Anh Duc"
        },
        {
            "id": "100077179487506",
            "count": 0,
            "name": "Mai Ng Xuân Anh"
        },
        {
            "id": "100051932492970",
            "count": 0,
            "name": "Hoàng V Sang"
        },
        {
            "id": "100073307092666",
            "count": 0,
            "name": "Trà Mi"
        },
        {
            "id": "100045694145946",
            "count": 0,
            "name": "Thao Nhi"
        }
    ],
    "time": 3
}